llm_ya_cli/__init__.py
llm_ya_cli/chat.py
llm_ya_cli/main.py
llm_ya_cli/utils/config.py
llm_ya_cli/utils/live_render.py
llm_ya_cli/utils/llm.py
llm_ya_cli-0.1.0.dist-info/licenses/LICENSE
llm_ya_cli-0.1.0.dist-info/licenses/licenses/LICENSE-Chatlas
llm_ya_cli-0.1.0.dist-info/licenses/licenses/LICENSE-Rich
llm_ya_cli-0.1.0.dist-info/METADATA
llm_ya_cli-0.1.0.dist-info/WHEEL
llm_ya_cli-0.1.0.dist-info/entry_points.txt
llm_ya_cli-0.1.0.dist-info/top_level.txt
llm_ya_cli-0.1.0.dist-info/RECORD
