Metadata-Version: 2.4
Name: llm-ya-cli
Version: 0.1.0
Summary: A CLI for LLMs.
Requires-Python: >=3.9
License-File: LICENSE
License-File: licenses/LICENSE-Chatlas
License-File: licenses/LICENSE-Rich
Requires-Dist: click>=8.1.8
Requires-Dist: platformdirs>=4.3.7
Requires-Dist: prompt-toolkit>=3.0.51
Requires-Dist: pydantic>=2.11.3
Requires-Dist: pydantic-ai>=0.0.46
Requires-Dist: rich>=14.0.0
Requires-Dist: tomli; python_full_version < "3.11"
Dynamic: license-file
